unbelieva/__init__.py
Pybelieva-0.0.2.dist-info/METADATA
Pybelieva-0.0.2.dist-info/WHEEL
Pybelieva-0.0.2.dist-info/top_level.txt
Pybelieva-0.0.2.dist-info/RECORD
