Metadata-Version: 2.1
Name: Pybelieva
Version: 0.0.2
Summary: Python wrapper for UnbelievaBoat API
Home-page: https://github.com/dev-cats/Pybelieva
Author: Mr_ChAI & korochun
Author-email: mr.kofe.edk@ya.ru
License: MIT
Project-URL: Documentation, https://github.com/dev-cats/Pybelieva/wiki/Documentation
Project-URL: Source, https://github.com/dev-cats/Pybelieva
Project-URL: Tracker, https://github.com/dev-cats/Pybelieva/issues
Keywords: UnbelievaBoat unbelievable pizza interface async aiohttp
Platform: UNKNOWN
Classifier: Development Status :: 6 - Mature
Classifier: Intended Audience :: Developers
Classifier: License :: OSI Approved :: MIT License
Classifier: Natural Language :: English
Classifier: Operating System :: OS Independent
Classifier: Programming Language :: Python :: 2
Classifier: Programming Language :: Python :: 3
Classifier: Topic :: Communications :: Chat
Requires-Dist: aiohttp
